LICENSE
MANIFEST.in
README.md
setup.py
chainerrl/__init__.py
chainerrl/action_value.py
chainerrl/agent.py
chainerrl/distribution.py
chainerrl/env.py
chainerrl/explorer.py
chainerrl/policy.py
chainerrl/q_function.py
chainerrl/recurrent.py
chainerrl/replay_buffer.py
chainerrl/v_function.py
chainerrl.egg-info/PKG-INFO
chainerrl.egg-info/SOURCES.txt
chainerrl.egg-info/dependency_links.txt
chainerrl.egg-info/requires.txt
chainerrl.egg-info/top_level.txt
chainerrl/agents/__init__.py
chainerrl/agents/a2c.py
chainerrl/agents/a3c.py
chainerrl/agents/acer.py
chainerrl/agents/al.py
chainerrl/agents/categorical_double_dqn.py
chainerrl/agents/categorical_dqn.py
chainerrl/agents/ddpg.py
chainerrl/agents/double_dqn.py
chainerrl/agents/double_iqn.py
chainerrl/agents/double_pal.py
chainerrl/agents/dpp.py
chainerrl/agents/dqn.py
chainerrl/agents/iqn.py
chainerrl/agents/nsq.py
chainerrl/agents/pal.py
chainerrl/agents/pcl.py
chainerrl/agents/pgt.py
chainerrl/agents/ppo.py
chainerrl/agents/reinforce.py
chainerrl/agents/residual_dqn.py
chainerrl/agents/sarsa.py
chainerrl/agents/soft_actor_critic.py
chainerrl/agents/td3.py
chainerrl/agents/trpo.py
chainerrl/envs/__init__.py
chainerrl/envs/abc.py
chainerrl/envs/ale.py
chainerrl/envs/multiprocess_vector_env.py
chainerrl/envs/serial_vector_env.py
chainerrl/experiments/__init__.py
chainerrl/experiments/collect_demos.py
chainerrl/experiments/evaluator.py
chainerrl/experiments/hooks.py
chainerrl/experiments/prepare_output_dir.py
chainerrl/experiments/train_agent.py
chainerrl/experiments/train_agent_async.py
chainerrl/experiments/train_agent_batch.py
chainerrl/explorers/__init__.py
chainerrl/explorers/additive_gaussian.py
chainerrl/explorers/additive_ou.py
chainerrl/explorers/boltzmann.py
chainerrl/explorers/epsilon_greedy.py
chainerrl/explorers/greedy.py
chainerrl/functions/__init__.py
chainerrl/functions/arctanh.py
chainerrl/functions/bound_by_tanh.py
chainerrl/functions/invert_gradients.py
chainerrl/functions/lower_triangular_matrix.py
chainerrl/functions/mellowmax.py
chainerrl/functions/mul_add.py
chainerrl/functions/scale_grad.py
chainerrl/functions/sum_arrays.py
