Metadata-Version: 2.1
Name: chainerrl
Version: 0.8.0
Summary: ChainerRL, a deep reinforcement learning library
Home-page: UNKNOWN
Author: Yasuhiro Fujita
Author-email: fujita@preferred.jp
License: MIT License
Platform: UNKNOWN
